spof/__init__.py
spof/json_util.py
spof/spof.py
spof-0.1.1.dist-info/METADATA
spof-0.1.1.dist-info/WHEEL
spof-0.1.1.dist-info/top_level.txt
spof-0.1.1.dist-info/RECORD
