Metadata-Version: 2.4
Name: spof
Version: 0.1.1
Summary: SPOF (Structured Prompt Output Framework) is an open-source Python framework for designing structured, maintainable, and type-safe prompts for Large Language Models (LLMs
Keywords: spof,llms,AI agents,openai,pydantic,python-dotenv,prompts,structured prompts
Requires-Python: >=3.9
Requires-Dist: pydantic>=2.11.5
